osbad/__init__.py
osbad/config.py
osbad/database.py
osbad/dbad.py
osbad/hyperparam.py
osbad/model.py
osbad/modval.py
osbad/py.typed
osbad/scaler.py
osbad/stats.py
osbad/viz.py
osbad-1.4.0.dist-info/METADATA
osbad-1.4.0.dist-info/WHEEL
osbad-1.4.0.dist-info/licenses/LICENSE
osbad-1.4.0.dist-info/RECORD
