Metadata-Version: 2.4
Name: osbad
Version: 1.4.0
Summary: OSBAD (Open-source Benchmark of Anomaly Detection)
Project-URL: Documentation, https://osbad.readthedocs.io/en/latest/
Project-URL: Repository, https://github.com/meichinpang/osbad/tree/master
Author-email: Mei-Chin Pang <mei-chin.pang@basf.com>
License-Expression: Apache-2.0
License-File: LICENSE
Keywords: anomaly detection,benchmark,hyperparameter tuning,outlier detection,statistics,unsupervised machine learning
Requires-Python: >=3.12
Requires-Dist: duckdb==1.3.2
Requires-Dist: fireducks>=1.4.0
Requires-Dist: llvmlite>=0.44.0
Requires-Dist: matplotlib>=3.10.5
Requires-Dist: natsort>=8.4.0
Requires-Dist: numpy<=2.2
Requires-Dist: optuna>=4.5.0
Requires-Dist: pandas>=2.3.2
Requires-Dist: plotly>=6.3.0
Requires-Dist: pyod>=2.0.5
Requires-Dist: scikit-learn>=1.7.1
Requires-Dist: seaborn>=0.13.2
Requires-Dist: tabulate>=0.9.0
Requires-Dist: torch>=2.8.0
